lambdawarmer/__init__.py
lambdawarmer/fakes.py
tests/__init__.py
tests/test_warmer.py
lambda_warmer_py-0.6.0.dist-info/LICENSE
lambda_warmer_py-0.6.0.dist-info/METADATA
lambda_warmer_py-0.6.0.dist-info/WHEEL
lambda_warmer_py-0.6.0.dist-info/top_level.txt
lambda_warmer_py-0.6.0.dist-info/RECORD
