Metadata-Version: 2.1
Name: lambda-warmer-py
Version: 0.6.0
Summary: keep lambdas warm and monitor cold starts with a simple decorator
Home-page: https://github.com/robhowley/lambda-warmer-py
Author: Rob Howley
Author-email: howley.robert@gmail.com
License: UNKNOWN
Platform: UNKNOWN
Classifier: Programming Language :: Python :: 3
Classifier: Programming Language :: Python :: 2
Classifier: License :: OSI Approved :: MIT License
Classifier: Operating System :: OS Independent
